{
  "MA": [
    "Casablanca",
    "Rabat",
    "Marrakech",
    "Fès",
    "Tanger",
    "Agadir",
    "Meknès",
    "Oujda",
    "Kénitra",
    "Tétouan",
    "Safi",
    "Essaouira",
    "El Jadida",
    "Béni Mellal",
    "Nador",
    "Taza",
    "Settat",
    "Khouribga",
    "Mohammédia",
    "Ouarzazate"
  ],
  "FR": [
    "Paris",
    "Marseille",
    "Lyon",
    "Toulouse",
    "Nice",
    "Nantes",
    "Strasbourg",
    "Montpellier",
    "Bordeaux",
    "Lille",
    "Rennes",
    "Reims",
    "Le Havre",
    "Saint-Étienne",
    "Toulon",
    "Grenoble",
    "Dijon",
    "Angers",
    "Nîmes",
    "Villeurbanne"
  ],
  "ES": [
    "Madrid",
    "Barcelone",
    "Valence",
    "Séville",
    "Saragosse",
    "Málaga",
    "Murcie",
    "Palma",
    "Las Palmas",
    "Bilbao"
  ],
  "IT": [
    "Rome",
    "Milan",
    "Naples",
    "Turin",
    "Palerme",
    "Gênes",
    "Bologne",
    "Florence",
    "Bari",
    "Catane"
  ],
  "DE": [
    "Berlin",
    "Hambourg",
    "Munich",
    "Cologne",
    "Francfort",
    "Stuttgart",
    "Düsseldorf",
    "Dortmund",
    "Essen",
    "Leipzig"
  ],
  "UK": [
    "Londres",
    "Birmingham",
    "Leeds",
    "Glasgow",
    "Sheffield",
    "Manchester",
    "Édimbourg",
    "Liverpool",
    "Bristol",
    "Cardiff"
  ],
  "BE": [
    "Bruxelles",
    "Anvers",
    "Gand",
    "Charleroi",
    "Liège",
    "Bruges",
    "Namur",
    "Louvain",
    "Mons",
    "Hasselt"
  ],
  "NL": [
    "Amsterdam",
    "Rotterdam",
    "La Haye",
    "Utrecht",
    "Eindhoven",
    "Tilburg",
    "Groningue",
    "Almere",
    "Breda",
    "Nimègue"
  ],
  "PT": [
    "Lisbonne",
    "Porto",
    "Amadora",
    "Braga",
    "Setúbal",
    "Coimbra",
    "Queluz",
    "Funchal",
    "Cacém",
    "Vila Nova de Gaia"
  ],
  "US": [
    "New York",
    "Los Angeles",
    "Chicago",
    "Houston",
    "Phoenix",
    "Philadelphie",
    "San Antonio",
    "San Diego",
    "Dallas",
    "San José"
  ],
  "CA": [
    "Toronto",
    "Montréal",
    "Vancouver",
    "Calgary",
    "Ottawa",
    "Edmonton",
    "Mississauga",
    "Winnipeg",
    "Québec",
    "Hamilton"
  ],
  "TN": [
    "Tunis",
    "Sfax",
    "Sousse",
    "Kairouan",
    "Bizerte",
    "Gabès",
    "Ariana",
    "Gafsa",
    "Kasserine",
    "Ben Arous"
  ],
  "DZ": [
    "Alger",
    "Oran",
    "Constantine",
    "Annaba",
    "Blida",
    "Batna",
    "Djelfa",
    "Sétif",
    "Sidi Bel Abbès",
    "Biskra"
  ],
  "SN": [
    "Dakar",
    "Thiès",
    "Kaolack",
    "Ziguinchor",
    "Saint-Louis",
    "Louga",
    "Mbour",
    "Rufisque",
    "Kolda",
    "Diourbel"
  ],
  "CI": [
    "Abidjan",
    "Bouaké",
    "Daloa",
    "Yamoussoukro",
    "San-Pédro",
    "Korhogo",
    "Man",
    "Divo",
    "Gagnoa",
    "Anyama"
  ],
  "CH": [
    "Zurich",
    "Genève",
    "Bâle",
    "Lausanne",
    "Berne",
    "Winterthour",
    "Lucerne",
    "Saint-Gall",
    "Lugano",
    "Bienne"
  ],
  "AE": [
    "Dubaï",
    "Abu Dhabi",
    "Sharjah",
    "Al Ain",
    "Ajman",
    "Ras Al Khaimah",
    "Fujairah",
    "Umm Al Quwain"
  ],
  "SA": [
    "Riyad",
    "Djeddah",
    "La Mecque",
    "Médine",
    "Dammam",
    "Taëf",
    "Tabuk",
    "Buraidah",
    "Khobar",
    "Khamis Mushait"
  ],
  "EG": [
    "Le Caire",
    "Alexandrie",
    "Gizeh",
    "Charm el-Cheikh",
    "Port-Saïd",
    "Suez",
    "Louxor",
    "El Mansourah",
    "Tanta",
    "Assiout"
  ],
  "TR": [
    "Istanbul",
    "Ankara",
    "Izmir",
    "Bursa",
    "Adana",
    "Gaziantep",
    "Konya",
    "Antalya",
    "Diyarbakır",
    "Mersin"
  ]
}
